django_rnx/__init__.py
django_rnx/templatetags/rnx.py
django_rnx-1.0.0.dist-info/METADATA
django_rnx-1.0.0.dist-info/WHEEL
django_rnx-1.0.0.dist-info/top_level.txt
django_rnx-1.0.0.dist-info/RECORD
