Metadata-Version: 2.4
Name: django-rnx
Version: 1.0.0
Summary: Django template tags for rnxJS reactive components
Home-page: https://github.com/BaryoDev/rnxjs
Author: Arnel Irobles
Author-email: Arnel Irobles <arnel@arnelirobles.com>
License: MPL-2.0
Project-URL: Homepage, https://github.com/BaryoDev/rnxjs
Project-URL: Documentation, https://github.com/BaryoDev/rnxjs/tree/main/packages/django-rnx
Project-URL: Repository, https://github.com/BaryoDev/rnxjs
Project-URL: Issues, https://github.com/BaryoDev/rnxjs/issues
Project-URL: Changelog, https://github.com/BaryoDev/rnxjs/releases
Keywords: django,rnxjs,reactive,components,template-tags
Classifier: Development Status :: 5 - Production/Stable
Classifier: Environment :: Web Environment
Classifier: Framework :: Django
Classifier: Framework :: Django :: 3.2
Classifier: Framework :: Django :: 4.0
Classifier: Framework :: Django :: 4.1
Classifier: Framework :: Django :: 4.2
Classifier: Framework :: Django :: 5.0
Classifier: Intended Audience :: Developers
Classifier: License :: OSI Approved :: Mozilla Public License 2.0 (MPL 2.0)
Classifier: Operating System :: OS Independent
Classifier: Programming Language :: Python
Classifier: Programming Language :: Python :: 3
Classifier: Programming Language :: Python :: 3.8
Classifier: Programming Language :: Python :: 3.9
Classifier: Programming Language :: Python :: 3.10
Classifier: Programming Language :: Python :: 3.11
Classifier: Programming Language :: Python :: 3.12
Classifier: Topic :: Internet :: WWW/HTTP
Classifier: Topic :: Internet :: WWW/HTTP :: Dynamic Content
Classifier: Topic :: Software Development :: Libraries :: Application Frameworks
Classifier: Topic :: Software Development :: Libraries :: Python Modules
Requires-Python: >=3.8
Requires-Dist: Django>=3.2
Provides-Extra: dev
Requires-Dist: pytest>=7.0; extra == "dev"
Requires-Dist: pytest-django>=4.5; extra == "dev"
Requires-Dist: pytest-cov>=4.0; extra == "dev"
Dynamic: author
Dynamic: home-page
Dynamic: requires-python
